{
  "designerVersion" : "1.7.25",
  "previousDesignerVersion" : "1.4.34",
  "id" : "ff316112-8ea0-426f-b603-fc73f2231c67",
  "name" : "newForm",
  "lastUpdate" : 1534255973525,
  "rows" : [ [ {
    "type" : "container",
    "dimension" : {
      "xs" : 12
    },
    "propertyValues" : { },
    "reference" : "faf0177c-9c09-46e6-8447-e1352e075968",
    "id" : "pbContainer",
    "rows" : [ [ {
      "type" : "component",
      "dimension" : {
        "md" : 12,
        "sm" : 12,
        "xs" : 12,
        "lg" : 12
      },
      "propertyValues" : {
        "labelHidden" : {
          "type" : "constant",
          "value" : false
        },
        "readonly" : {
          "type" : "constant",
          "value" : false
        },
        "level" : {
          "type" : "constant",
          "value" : "Level 1"
        },
        "cssClasses" : {
          "type" : "constant",
          "value" : ""
        },
        "widgetId" : {
          "type" : "constant",
          "value" : "pbTitle"
        },
        "isDisplayed" : {
          "type" : "constant",
          "value" : true
        },
        "label" : {
          "type" : "constant"
        },
        "text" : {
          "type" : "interpolation",
          "value" : "{{ task.displayName }}"
        },
        "alignment" : {
          "type" : "constant",
          "value" : "center"
        },
        "class" : {
          "type" : "constant",
          "value" : "org.bonitasoft.web.designer.experimental.parametrizedWidget.TitleWidget"
        },
        "dimension" : {
          "type" : "constant",
          "value" : 12
        }
      },
      "reference" : "8ce38710-2895-4c39-ba87-8470c6e673b9",
      "id" : "pbTitle"
    } ], [ {
      "type" : "component",
      "dimension" : {
        "md" : 12,
        "sm" : 12,
        "xs" : 12,
        "lg" : 12
      },
      "propertyValues" : {
        "labelHidden" : {
          "type" : "constant",
          "value" : false
        },
        "readonly" : {
          "type" : "constant",
          "value" : false
        },
        "cssClasses" : {
          "type" : "constant",
          "value" : ""
        },
        "widgetId" : {
          "type" : "constant",
          "value" : "pbText"
        },
        "isDisplayed" : {
          "type" : "constant",
          "value" : true
        },
        "label" : {
          "type" : "constant"
        },
        "text" : {
          "type" : "interpolation",
          "value" : "{{ task.displayDescription }}"
        },
        "alignment" : {
          "type" : "constant",
          "value" : "left"
        },
        "class" : {
          "type" : "constant",
          "value" : "org.bonitasoft.web.designer.experimental.parametrizedWidget.TextWidget"
        },
        "dimension" : {
          "type" : "constant",
          "value" : 12
        },
        "allowHTML" : {
          "type" : "constant",
          "value" : true
        }
      },
      "reference" : "f5333f84-6ab9-4bc2-be6a-82f5c980988e",
      "id" : "pbText"
    } ] ]
  } ], [ {
    "type" : "formContainer",
    "dimension" : {
      "xs" : 12
    },
    "propertyValues" : { },
    "reference" : "bcb9beaa-44c7-452a-aee0-6890d763cb25",
    "id" : "pbFormContainer",
    "container" : {
      "type" : "container",
      "dimension" : {
        "xs" : 12
      },
      "propertyValues" : { },
      "reference" : "6fb25418-c040-4d97-b23b-ddfc4d4d35ea",
      "id" : "pbContainer",
      "rows" : [ [ {
        "type" : "component",
        "dimension" : {
          "xs" : 12,
          "sm" : 12,
          "md" : 6,
          "lg" : 6
        },
        "propertyValues" : {
          "cssClasses" : {
            "type" : "constant",
            "value" : ""
          },
          "hidden" : {
            "type" : "constant",
            "value" : false
          },
          "required" : {
            "type" : "constant",
            "value" : false
          },
          "minLength" : {
            "type" : "constant",
            "value" : ""
          },
          "maxLength" : {
            "type" : "constant",
            "value" : ""
          },
          "readOnly" : {
            "type" : "constant",
            "value" : false
          },
          "labelHidden" : {
            "type" : "constant",
            "value" : false
          },
          "label" : {
            "type" : "interpolation",
            "value" : "Nombre cliente"
          },
          "labelPosition" : {
            "type" : "constant",
            "value" : "top"
          },
          "labelWidth" : {
            "type" : "constant",
            "value" : 4
          },
          "placeholder" : {
            "type" : "interpolation"
          },
          "value" : {
            "type" : "variable"
          },
          "type" : {
            "type" : "constant",
            "value" : "text"
          },
          "min" : {
            "type" : "constant"
          },
          "max" : {
            "type" : "constant"
          },
          "step" : {
            "type" : "constant",
            "value" : 1
          }
        },
        "reference" : "926ad093-6149-4b0b-83de-71e40ddb2380",
        "id" : "pbInput"
      }, {
        "type" : "component",
        "dimension" : {
          "xs" : 12,
          "sm" : 12,
          "md" : 6,
          "lg" : 6
        },
        "propertyValues" : {
          "cssClasses" : {
            "type" : "constant",
            "value" : ""
          },
          "hidden" : {
            "type" : "constant",
            "value" : false
          },
          "required" : {
            "type" : "constant",
            "value" : false
          },
          "minLength" : {
            "type" : "constant",
            "value" : ""
          },
          "maxLength" : {
            "type" : "constant",
            "value" : ""
          },
          "readOnly" : {
            "type" : "constant",
            "value" : false
          },
          "labelHidden" : {
            "type" : "constant",
            "value" : false
          },
          "label" : {
            "type" : "interpolation",
            "value" : "Apellido"
          },
          "labelPosition" : {
            "type" : "constant",
            "value" : "top"
          },
          "labelWidth" : {
            "type" : "constant",
            "value" : 4
          },
          "placeholder" : {
            "type" : "interpolation"
          },
          "value" : {
            "type" : "variable"
          },
          "type" : {
            "type" : "constant",
            "value" : "text"
          },
          "min" : {
            "type" : "constant"
          },
          "max" : {
            "type" : "constant"
          },
          "step" : {
            "type" : "constant",
            "value" : 1
          }
        },
        "reference" : "0fa21ae7-3c55-4432-8811-f159706b5e14",
        "id" : "pbInput"
      } ], [ {
        "type" : "component",
        "dimension" : {
          "xs" : 12,
          "sm" : 12,
          "md" : 12,
          "lg" : 12
        },
        "propertyValues" : {
          "cssClasses" : {
            "type" : "constant",
            "value" : ""
          },
          "hidden" : {
            "type" : "constant",
            "value" : false
          },
          "readOnly" : {
            "type" : "constant",
            "value" : false
          },
          "required" : {
            "type" : "constant",
            "value" : false
          },
          "minLength" : {
            "type" : "constant",
            "value" : ""
          },
          "maxLength" : {
            "type" : "constant",
            "value" : ""
          },
          "labelHidden" : {
            "type" : "constant",
            "value" : false
          },
          "label" : {
            "type" : "interpolation",
            "value" : "Comentarios"
          },
          "labelPosition" : {
            "type" : "constant",
            "value" : "top"
          },
          "labelWidth" : {
            "type" : "constant",
            "value" : 4
          },
          "value" : {
            "type" : "variable"
          }
        },
        "reference" : "33dae63d-bc6d-4b52-88f8-88c717556afc",
        "id" : "pbTextarea"
      } ], [ {
        "type" : "component",
        "dimension" : {
          "md" : 12,
          "sm" : 12,
          "xs" : 12,
          "lg" : 12
        },
        "propertyValues" : {
          "removeItem" : {
            "type" : "variable"
          },
          "cssClasses" : {
            "type" : "constant",
            "value" : ""
          },
          "widgetId" : {
            "type" : "constant",
            "value" : "pbButton"
          },
          "buttonStyle" : {
            "type" : "constant",
            "value" : "primary"
          },
          "isDisplayed" : {
            "type" : "constant",
            "value" : true
          },
          "label" : {
            "type" : "constant",
            "value" : "Submit"
          },
          "dataToSend" : {
            "type" : "expression",
            "value" : "formOutput"
          },
          "labelHidden" : {
            "type" : "constant",
            "value" : false
          },
          "readonly" : {
            "type" : "constant",
            "value" : false
          },
          "collectionPosition" : {
            "type" : "constant"
          },
          "targetUrlOnSuccess" : {
            "type" : "interpolation",
            "value" : "/bonita"
          },
          "action" : {
            "type" : "constant",
            "value" : "Submit task"
          },
          "collectionToModify" : {
            "type" : "variable"
          },
          "valueToAdd" : {
            "type" : "expression"
          },
          "disabled" : {
            "type" : "expression",
            "value" : "$form.$invalid"
          },
          "alignment" : {
            "type" : "constant",
            "value" : "center"
          },
          "class" : {
            "type" : "constant",
            "value" : "org.bonitasoft.web.designer.experimental.parametrizedWidget.ButtonWidget"
          },
          "dimension" : {
            "type" : "constant",
            "value" : 12
          }
        },
        "reference" : "fb380ea5-7794-4122-aa81-4916185a1b07",
        "id" : "pbButton"
      } ] ]
    }
  } ] ],
  "assets" : [ {
    "id" : "7fec1d43-64d8-4ded-b65e-ec4b829833c7",
    "name" : "localization.json",
    "type" : "json",
    "order" : 0,
    "external" : false
  }, {
    "id" : "ff6d4295-ed73-46e3-b819-dc9729517b40",
    "name" : "ui-bootstrap-tpls-0.13.0.min.js",
    "type" : "js",
    "order" : 2,
    "external" : false
  }, {
    "id" : "dfa944d9-745e-4e3b-a314-56f6e52216f3",
    "name" : "style.css",
    "type" : "css",
    "order" : 1,
    "external" : false
  } ],
  "inactiveAssets" : [ ],
  "data" : {
    "task" : {
      "type" : "url",
      "value" : "../API/bpm/userTask/{{taskId}}",
      "exposed" : false
    },
    "formInput" : {
      "type" : "json",
      "value" : "{ }",
      "exposed" : false
    },
    "formOutput" : {
      "type" : "expression",
      "value" : "return {\n\n};",
      "exposed" : false
    },
    "context" : {
      "type" : "url",
      "value" : "../API/bpm/userTask/{{taskId}}/context",
      "exposed" : false
    },
    "taskId" : {
      "type" : "urlparameter",
      "value" : "id",
      "exposed" : false
    }
  },
  "uuid" : "ff316112-8ea0-426f-b603-fc73f2231c67",
  "type" : "form"
}